Workbook

Sheet Dashboard
A1: PRICEPILOT AI | TEST PROGRESS DASHBOARD
A4: Total API Endpoints | D4: API Tests Executed | G4: API Pass Rate | J4: Open API Failures
A5: =COUNTA('API Test Log'!A5:A41) -> 37 | D5: =COUNTIF('API Test Log'!H5:H41,"Passed")+COUNTIF('API Test Log'!H5:H41,"Failed")+COUNTIF('API Test Log'!H5:H41,"Blocked")+COUNTIF('API Test Log'!H5:H41,"Skipped") -> 37 | G5: =IFERROR(COUNTIF('API Test Log'!H5:H41,"Passed")/(COUNTIF('API Test Log'!H5:H41,"Passed")+COUNTIF('API Test Log'!H5:H41,"Failed")),0) -> 0.91666667 | J5: =COUNTIF('API Test Log'!H5:H41,"Failed") -> 3
A7: Total Functional Cases | D7: Functional Cases Executed | G7: Functional Pass Rate | J7: Functional Failures
A8: =COUNTA('Test Cases'!A4:A45) -> 42 | D8: =COUNTIF('Test Cases'!H4:H45,"Passed")+COUNTIF('Test Cases'!H4:H45,"Failed")+COUNTIF('Test Cases'!H4:H45,"Blocked")+COUNTIF('Test Cases'!H4:H45,"Skipped") -> 15 | G8: =IFERROR(COUNTIF('Test Cases'!H4:H45,"Passed")/(COUNTIF('Test Cases'!H4:H45,"Passed")+COUNTIF('Test Cases'!H4:H45,"Failed")),0) -> 1 | J8: =COUNTIF('Test Cases'!H4:H45,"Failed") -> 0
A11: API Status | B11: Count | D11: Functional Status | E11: Count | G11: Module | H11: Passed | I11: Failed | J11: Not Run
A12: Passed | B12: =COUNTIF('API Test Log'!H5:H41,A12) -> 33 | D12: Passed | E12: =COUNTIF('Test Cases'!H4:H45,D12) -> 15 | G12: Authentication | H12: =COUNTIFS('API Test Log'!$B$5:$B$41,G12,'API Test Log'!$H$5:$H$41,"Passed") -> 4 | I12: =COUNTIFS('API Test Log'!$B$5:$B$41,G12,'API Test Log'!$H$5:$H$41,"Failed") -> 0 | J12: =COUNTIFS('API Test Log'!$B$5:$B$41,G12,'API Test Log'!$H$5:$H$41,"Not Run") -> 0
A13: Failed | B13: =COUNTIF('API Test Log'!H5:H41,A13) -> 3 | D13: Failed | E13: =COUNTIF('Test Cases'!H4:H45,D13) -> 0 | G13: Users | H13: =COUNTIFS('API Test Log'!$B$5:$B$41,G13,'API Test Log'!$H$5:$H$41,"Passed") -> 3 | I13: =COUNTIFS('API Test Log'!$B$5:$B$41,G13,'API Test Log'!$H$5:$H$41,"Failed") -> 0 | J13: =COUNTIFS('API Test Log'!$B$5:$B$41,G13,'API Test Log'!$H$5:$H$41,"Not Run") -> 0
A14: Not Run | B14: =COUNTIF('API Test Log'!H5:H41,A14) -> 0 | D14: Not Run | E14: =COUNTIF('Test Cases'!H4:H45,D14) -> 27 | G14: Organizations | H14: =COUNTIFS('API Test Log'!$B$5:$B$41,G14,'API Test Log'!$H$5:$H$41,"Passed") -> 4 | I14: =COUNTIFS('API Test Log'!$B$5:$B$41,G14,'API Test Log'!$H$5:$H$41,"Failed") -> 0 | J14: =COUNTIFS('API Test Log'!$B$5:$B$41,G14,'API Test Log'!$H$5:$H$41,"Not Run") -> 0
A15: Blocked | B15: =COUNTIF('API Test Log'!H5:H41,A15) -> 1 | D15: Blocked | E15: =COUNTIF('Test Cases'!H4:H45,D15) -> 0 | G15: Categories | H15: =COUNTIFS('API Test Log'!$B$5:$B$41,G15,'API Test Log'!$H$5:$H$41,"Passed") -> 2 | I15: =COUNTIFS('API Test Log'!$B$5:$B$41,G15,'API Test Log'!$H$5:$H$41,"Failed") -> 0 | J15: =COUNTIFS('API Test Log'!$B$5:$B$41,G15,'API Test Log'!$H$5:$H$41,"Not Run") -> 0
A16: Skipped | B16: =COUNTIF('API Test Log'!H5:H41,A16) -> 0 | D16: Skipped | E16: =COUNTIF('Test Cases'!H4:H45,D16) -> 0 | G16: Products | H16: =COUNTIFS('API Test Log'!$B$5:$B$41,G16,'API Test Log'!$H$5:$H$41,"Passed") -> 8 | I16: =COUNTIFS('API Test Log'!$B$5:$B$41,G16,'API Test Log'!$H$5:$H$41,"Failed") -> 0 | J16: =COUNTIFS('API Test Log'!$B$5:$B$41,G16,'API Test Log'!$H$5:$H$41,"Not Run") -> 0
G17: Competitors | H17: =COUNTIFS('API Test Log'!$B$5:$B$41,G17,'API Test Log'!$H$5:$H$41,"Passed") -> 4 | I17: =COUNTIFS('API Test Log'!$B$5:$B$41,G17,'API Test Log'!$H$5:$H$41,"Failed") -> 2 | J17: =COUNTIFS('API Test Log'!$B$5:$B$41,G17,'API Test Log'!$H$5:$H$41,"Not Run") -> 0
G18: Pricing Engine | H18: =COUNTIFS('API Test Log'!$B$5:$B$41,G18,'API Test Log'!$H$5:$H$41,"Passed") -> 3 | I18: =COUNTIFS('API Test Log'!$B$5:$B$41,G18,'API Test Log'!$H$5:$H$41,"Failed") -> 1 | J18: =COUNTIFS('API Test Log'!$B$5:$B$41,G18,'API Test Log'!$H$5:$H$41,"Not Run") -> 0
G19: Sales | H19: =COUNTIFS('API Test Log'!$B$5:$B$41,G19,'API Test Log'!$H$5:$H$41,"Passed") -> 1 | I19: =COUNTIFS('API Test Log'!$B$5:$B$41,G19,'API Test Log'!$H$5:$H$41,"Failed") -> 0 | J19: =COUNTIFS('API Test Log'!$B$5:$B$41,G19,'API Test Log'!$H$5:$H$41,"Not Run") -> 0
G20: AI v2 | H20: =COUNTIFS('API Test Log'!$B$5:$B$41,G20,'API Test Log'!$H$5:$H$41,"Passed") -> 2 | I20: =COUNTIFS('API Test Log'!$B$5:$B$41,G20,'API Test Log'!$H$5:$H$41,"Failed") -> 0 | J20: =COUNTIFS('API Test Log'!$B$5:$B$41,G20,'API Test Log'!$H$5:$H$41,"Not Run") -> 0
G21: System | H21: =COUNTIFS('API Test Log'!$B$5:$B$41,G21,'API Test Log'!$H$5:$H$41,"Passed") -> 2 | I21: =COUNTIFS('API Test Log'!$B$5:$B$41,G21,'API Test Log'!$H$5:$H$41,"Failed") -> 0 | J21: =COUNTIFS('API Test Log'!$B$5:$B$41,G21,'API Test Log'!$H$5:$H$41,"Not Run") -> 0

Sheet API Test Log
A1: PRICEPILOT AI | DYNAMIC API TEST EXECUTION LOG
A4: Test ID | B4: Module | C4: Method | D4: Endpoint | E4: Operation | F4: Priority | G4: Auth Required | H4: Test Status | I4: HTTP Status
A5: API-001 | B5: Authentication | C5: POST | D5: /api/v1/auth/register | E5: register | F5: High | G5: Yes | H5: Passed | I5: 200
A6: API-002 | B6: Authentication | C6: POST | D6: /api/v1/auth/login | E6: login | F6: High | G6: Yes | H6: Passed | I6: 200
A7: API-003 | B7: Authentication | C7: POST | D7: /api/v1/auth/token | E7: token | F7: High | G7: No / verify route policy | H7: Passed | I7: 200
A8: API-004 | B8: Authentication | C8: GET | D8: /api/v1/auth/me | E8: me | F8: High | G8: Yes | H8: Passed | I8: 200
A9: API-005 | B9: Users | C9: GET | D9: /api/v1/users/ | E9: users | F9: Medium | G9: Yes | H9: Passed | I9: 200
A10: API-006 | B10: Users | C10: GET | D10: /api/v1/users/{user_id} | E10: {user_id} (ID-based) | F10: Medium | G10: Yes | H10: Passed | I10: 200
A11: API-007 | B11: Users | C11: PUT | D11: /api/v1/users/{user_id} | E11: {user_id} (ID-based) | F11: Medium | G11: Yes | H11: Passed | I11: 200
A12: API-008 | B12: Organizations | C12: GET | D12: /api/v1/organizations/ | E12: organizations | F12: Medium | G12: Yes | H12: Passed | I12: 200
A13: API-009 | B13: Organizations | C13: POST | D13: /api/v1/organizations/ | E13: organizations | F13: Medium | G13: Yes | H13: Passed | I13: 200
A14: API-010 | B14: Organizations | C14: GET | D14: /api/v1/organizations/{org_id} | E14: {org_id} (ID-based) | F14: Medium | G14: Yes | H14: Passed | I14: 200
A15: API-011 | B15: Organizations | C15: POST | D15: /api/v1/organizations/{org_id}/members | E15: members (ID-based) | F15: Medium | G15: Yes | H15: Passed | I15: 200
A16: API-012 | B16: Categories | C16: POST | D16: /api/v1/categories/ | E16: categories | F16: Medium | G16: Yes | H16: Passed | I16: 200
A17: API-013 | B17: Categories | C17: GET | D17: /api/v1/categories/organization/{org_id} | E17: {org_id} (ID-based) | F17: Medium | G17: Yes | H17: Passed | I17: 200
A18: API-014 | B18: Products | C18: POST | D18: /api/v1/products/ | E18: products | F18: Medium | G18: Yes | H18: Passed | I18: 200
... A36: API-032 | B36: Sales | C36: POST | D36: /api/v1/sales/ | E36: sales | F36: Medium | G36: Yes | H36: Passed | I36: 200
A37: API-033 | B37: Sales | C37: GET | D37: /api/v1/sales/analytics/{organization_id} | E37: {organization_id} (ID-based) | F37: Medium | G37: Yes | H37: Blocked
A38: API-034 | B38: AI v2 | C38: POST | D38: /api/v2/ai/gemini | E38: gemini | F38: High | G38: Yes | H38: Passed | I38: 200
A39: API-035 | B39: AI v2 | C39: POST | D39: /api/v2/ai/predict | E39: predict | F39: High | G39: Yes | H39: Passed | I39: 200
A40: API-036 | B40: System | C40: GET | D40: / | F40: Medium | G40: No | H40: Passed | I40: 200
A41: API-037 | B41: System | C41: GET | D41: /health | E41: health | F41: Medium | G41: No | H41: Passed | I41: 200

Sheet Test Cases
A1: PRICEPILOT AI | FUNCTIONAL & END-TO-END TEST CASES
A3: Case ID | B3: Test Area | C3: Scenario | D3: Preconditions / Test Data | E3: Steps to Execute | F3: Expected Result | G3: Actual Result | H3: Status | I3: Severity
A4: TC-001 | B4: Environment | C4: Backend health endpoint | D4: Backend running at localhost:8000 | E4: GET /health in Swagger or browser | F4: Healthy response with expected status; service is reachable | H4: Passed | I4: Medium
A5: TC-002 | B5: Environment | C5: OpenAPI documentation loads | D5: Backend running | E5: Open /docs and inspect listed routes | F5: Swagger UI loads and route inventory matches backend OpenAPI | H5: Passed | I5: Medium
A6: TC-003 | B6: Authentication | C6: Register valid user | D6: Unique test email; valid password | E6: POST /api/v1/auth/register with valid schema | F6: User is created and response matches schema | H6: Passed | I6: Medium
A7: TC-004 | B7: Authentication | C7: Register duplicate email | D7: Email already registered | E7: Repeat register with same email | F7: Clear validation/conflict response; no duplicate user | H7: Passed | I7: Medium
A8: TC-005 | B8: Authentication | C8: Login valid credentials | D8: Registered test account | E8: POST /api/v1/auth/login | F8: Token returned according to schema | H8: Passed | I8: Medium
A9: TC-006 | B9: Authentication | C9: Login invalid password | D9: Registered email, wrong password | E9: Submit login with wrong password | F9: 401/403 or documented safe error; no token exposed | H9: Passed | I9: Medium
A10: TC-007 | B10: Authentication | C10: Current user with valid token | D10: Valid access token | E10: GET /api/v1/auth/me with Bearer token | F10: Returns the authenticated user | H10: Passed | I10: Medium
A11: TC-008 | B11: Authentication | C11: Protected route without token | D11: No Authorization header | E11: Call protected endpoint without token | F11: 401/403; no private data returned | H11: Passed | I11: Medium
A12: TC-009 | B12: Authorization | C12: Organization data isolation | D12: Two test organizations/users | E12: Call org-scoped endpoints as each user | F12: User sees only authorized organization data | H12: Passed | I12: Medium
A13: TC-010 | B13: Organizations | C13: Create organization | D13: Authenticated user and valid payload | E13: POST /api/v1/organizations/ | F13: Organization created and returned | H13: Passed | I13: Medium
A14: TC-011 | B14: Organizations | C14: Add organization member | D14: Existing org and valid member | E14: POST /api/v1/organizations/{org_id}/members | F14: Member added with permitted role | H14: Passed | I14: Medium
A15: TC-012 | B15: Categories | C15: Create category | D15: Existing authorized organization | E15: POST /api/v1/categories/ | F15: Category created and linked to organization | H15: Passed | I15: Medium
... A45: TC-042 | B45: Regression | C45: Run critical workflow | D45: User → org → product → competitor price → recommendation | E45: Execute linked workflow using test records | F45: IDs/relationships remain consistent through workflow | H45: Not Run | I45: Medium

Sheet Read Me
A1: PRICEPILOT AI | TEST PROGRESS WORKBOOK
A3: Purpose | B3: Track endpoint execution, functional test cases, defects, and project test progress in one Excel workbook.
A4: 1. Start here | B4: Open Dashboard first. It summarizes the status in API Test Log and Test Cases.
A5: 2. API Test Log | B5: For each endpoint, update Test Status, HTTP Status, Actual Result / Notes, tester, date, duration, and retest status. Yellow cells are intended for input.
A6: 3. Test Cases | B6: Execute the 42 functional, negative, integration, frontend, ML, security, and regression checks. Change Status only after checking expected behavior.
A7: 4. Defects & Notes | B7: Record reproducible failures, severity, ownership, fix, and retest result. Add the Defect ID back to the relevant test row.
A8: 5. Dashboard | B8: Charts and KPIs are formula-driven from the log. They update when statuses are changed in Excel and recalculated.
A9: Status meanings | B9: Not Run = not executed; Passed = expected behavior verified; Failed = incorrect result; Blocked = unable to test due to dependency; Skipped = intentionally not executed.
A10: Evidence rule | B10: A 200 response alone is not enough. Verify schema, database side effects, authorization, and business logic.
A11: Security warning | B11: Never paste passwords, live bearer tokens, API keys, or production personal data into this workbook.
A12: Excel note | B12: Open in desktop Microsoft Excel with calculation set to Automatic. If charts do not refresh, press Ctrl+Alt+F9 to force recalculation.
A13: Important project note | B13: The pricing endpoint paths should be verified against the current backend /openapi.json before marking those cases as available; do not infer that a listed path is implemented.

Sheet Testing Guide
A1: PricePilot AI — API Testing Guide
A2: Purpose | B2: Track API endpoint validation based on the supplied Swagger endpoint inventory.
A3: How to test | B3: Open http://localhost:8000/docs, authorize with a valid bearer token where required, open an endpoint, click Try it out, enter valid request data, then Execute.
A4: Passed | B4: Use only after the endpoint returns the expected response and the result is checked. HTTP 200 alone does not prove business logic is correct.
A5: Pending | B5: Endpoint has not been verified in the evidence provided; test it with valid data before changing its status.
A6: 401 / 403 | B6: Check bearer token, expiry, permissions, and organization membership.
A7: 422 | B7: Check request body, path/query parameters, and the validation response detail.
A8: 500 | B8: Inspect backend terminal logs; do not mark the endpoint passed.
A9: Important | B9: POST/PUT/DELETE endpoints may change database records. Use test data and confirm side effects before testing destructive operations.
A10: AI prediction | B10: Verify input feature names/types, finite numeric output, timestamp, model version, and compare prediction with a known test case when ground truth is available.
A11: Security | B11: Do not store real bearer tokens, passwords, API keys, or secrets in this workbook.
